Metadata-Version: 2.4
Name: mqrpy
Version: 0.6.5
Summary: Design and manufacturing quality improvement toolkit
Author: Nikolas Crossan, Kevin Otto
Maintainer-email: mqr developers <mqr.python@gmail.com>
Project-URL: Documentation, https://nklsxn.github.io/mqr/latest/
Project-URL: Repository, https://github.com/nklsxn/mqr
Keywords: quality,manufacturing,six sigma,dmaic,design of experiments,anova,grr,msa,statistical quality control,sqc,statistical process control,spc,robust design,response surface design
Classifier: Programming Language :: Python :: 3
Classifier: License :: OSI Approved :: BSD License
Classifier: Operating System :: OS Independent
Classifier: Intended Audience :: Manufacturing
Requires-Python: >=3.11
License-File: LICENSE.txt
Requires-Dist: ipython
Requires-Dist: pytest
Requires-Dist: markdown>=3.6
Requires-Dist: matplotlib>=3.8
Requires-Dist: mergedeep>=1.3
Requires-Dist: numpy>=2.0
Requires-Dist: openpyxl>=3.1
Requires-Dist: pandas>=2.2
Requires-Dist: probscale>=0.2
Requires-Dist: pydoe3>=1.0
Requires-Dist: scipy>=1.14
Requires-Dist: seaborn>=0.13
Requires-Dist: statsmodels>=0.14
Dynamic: license-file
